streamtasks/__init__.py
streamtasks/__main__.py
streamtasks/asgi.py
streamtasks/asgiserver.py
streamtasks/bin.py
streamtasks/connection.py
streamtasks/debugging.py
streamtasks/env.py
streamtasks/error.py
streamtasks/pydanticdb.py
streamtasks/rawdatabuffer.py
streamtasks/utils.py
streamtasks/worker.py
streamtasks/client/__init__.py
streamtasks/client/broadcast.py
streamtasks/client/discovery.py
streamtasks/client/fetch.py
streamtasks/client/receiver.py
streamtasks/client/signal.py
streamtasks/client/topic.py
streamtasks/media/__init__.py
streamtasks/media/audio.py
streamtasks/media/codec.py
streamtasks/media/container.py
streamtasks/media/packet.py
streamtasks/media/util.py
streamtasks/media/video.py
streamtasks/media/video_perf.cp311-win_amd64.pyd
streamtasks/media/video_perf.pyi
streamtasks/media/video_perf_all.cpp
streamtasks/message/__init__.py
streamtasks/message/types.py
streamtasks/message/utils.py
streamtasks/net/__init__.py
streamtasks/net/helpers.py
streamtasks/net/messages.py
streamtasks/net/serialization.py
streamtasks/net/utils.py
streamtasks/services/__init__.py
streamtasks/services/constants.py
streamtasks/services/discovery.py
streamtasks/system/__init__.py
streamtasks/system/builder.py
streamtasks/system/configurators.py
streamtasks/system/connection_manager.py
streamtasks/system/fntask.py
streamtasks/system/helpers.py
streamtasks/system/named_topic_manager.py
streamtasks/system/secret_manager.py
streamtasks/system/task.py
streamtasks/system/task_web.py
streamtasks/system/assets/public/.gitignore
streamtasks/system/assets/public/index.html
streamtasks/system/assets/public/main.js
streamtasks/system/assets/public/configurators/multitrackio.js
streamtasks/system/assets/public/configurators/namedinput.js
streamtasks/system/assets/public/configurators/namedoutput.js
streamtasks/system/assets/public/configurators/notfound.js
streamtasks/system/assets/public/configurators/static.js
streamtasks/system/assets/public/configurators/switch.js
streamtasks-0.1.13.dist-info/LICENSE
streamtasks-0.1.13.dist-info/METADATA
streamtasks-0.1.13.dist-info/WHEEL
streamtasks-0.1.13.dist-info/entry_points.txt
streamtasks-0.1.13.dist-info/top_level.txt
streamtasks-0.1.13.dist-info/RECORD
