Metadata-Version: 2.1
Name: streamtasks
Version: 0.1.13
Summary: A python task orchestrator to simplify real-time, static data pipelines.
Author: leopf
License: MIT License
Project-URL: Homepage, https://github.com/leopf/streamtasks
Project-URL: Documentation, https://leopf.github.io/streamtasks/
Project-URL: Repository, https://github.com/leopf/streamtasks
License-File: LICENSE
Requires-Dist: typing-extensions <5.0.0,>=4.0.0
Requires-Dist: lark <2.0.0,>=1.1.9
Requires-Dist: msgpack <2.0.0,>=1.0.0
Requires-Dist: pydantic <3.0.0,>=2.7.1
Requires-Dist: numpy <2.0.0,>=1.26.4
Requires-Dist: uvicorn[standard] <1.0.0,>=0.29.0
Requires-Dist: websockets >=12.0.0
Provides-Extra: dev
Requires-Dist: ruff ; extra == 'dev'
Provides-Extra: inference
Requires-Dist: speechbrain <2.0.0,>=1.0.0 ; extra == 'inference'
Requires-Dist: torch <3.0.0,>=2.0.0 ; extra == 'inference'
Requires-Dist: llama-cpp-python <1.0.0,>=0.2.0 ; extra == 'inference'
Requires-Dist: transformers <5.0.0,>=4.30.0 ; extra == 'inference'
Provides-Extra: media
Requires-Dist: av <13.0.0,>=12.0.0 ; extra == 'media'
Requires-Dist: opencv-python <5.0.0,>=4.9.0.80 ; extra == 'media'
Requires-Dist: sounddevice <1.0.0,>=0.4.0 ; extra == 'media'
Requires-Dist: mss <10.0.0,>=9.0.0 ; extra == 'media'
Requires-Dist: pillow >=10.0.0 ; extra == 'media'
Provides-Extra: testing
Requires-Dist: httpx <1.0.0,>=0.27.0 ; extra == 'testing'
